asr_evaluation/__init__.py
asr_evaluation/__main__.py
asr_evaluation/asr_evaluation.py
asr_evaluation-2.0.4.dist-info/METADATA
asr_evaluation-2.0.4.dist-info/RECORD
asr_evaluation-2.0.4.dist-info/WHEEL
asr_evaluation-2.0.4.dist-info/entry_points.txt
asr_evaluation-2.0.4.dist-info/top_level.txt
