Metadata-Version: 2.1
Name: asr-evaluation
Version: 2.0.4
Summary: Evaluating ASR (automatic speech recognition) hypotheses, i.e. computing word error rate.
Home-page: UNKNOWN
Author: Ben Lambert
Author-email: blambert@gmail.com
License: LICENSE.txt
Keywords: word,error,rate,asr,speech,recognition
Platform: UNKNOWN
Classifier: Development Status :: 5 - Production/Stable
Classifier: Environment :: Console
Classifier: Programming Language :: Python
Classifier: Topic :: Scientific/Engineering :: Artificial Intelligence
Classifier: Topic :: Text Processing
Classifier: Topic :: Utilities
Classifier: License :: OSI Approved :: Apache Software License
Requires-Dist: edit-distance
Requires-Dist: termcolor
